AUTHORS
COPYRIGHT
MANIFEST.in
README.md
setup.py
django_gencal.egg-info/PKG-INFO
django_gencal.egg-info/SOURCES.txt
django_gencal.egg-info/dependency_links.txt
django_gencal.egg-info/not-zip-safe
django_gencal.egg-info/top_level.txt
docs/.DS_Store
docs/.gitignore
docs/Makefile
docs/build_html.sh
docs/build/.DS_Store
docs/build/doctrees/environment.pickle
docs/build/doctrees/index.doctree
docs/build/doctrees/installation.doctree
docs/build/doctrees/project.doctree
docs/build/doctrees/templatetag.doctree
docs/build/html/.buildinfo
docs/build/html/genindex.html
docs/build/html/index.html
docs/build/html/installation.html
docs/build/html/modindex.html
docs/build/html/objects.inv
docs/build/html/project.html
docs/build/html/search.html
docs/build/html/searchindex.js
docs/build/html/templatetag.html
docs/build/html/_sources/index.txt
docs/build/html/_sources/installation.txt
docs/build/html/_sources/project.txt
docs/build/html/_sources/templatetag.txt
docs/build/html/_static/basic.css
docs/build/html/_static/default.css
docs/build/html/_static/doctools.js
docs/build/html/_static/file.png
docs/build/html/_static/jquery.js
docs/build/html/_static/minus.png
docs/build/html/_static/plus.png
docs/build/html/_static/pygments.css
docs/build/html/_static/searchtools.js
docs/source/conf.py
docs/source/index.rst
docs/source/installation.rst
docs/source/templatetag.rst
gencal/__init__.py
gencal/tests.py
gencal/templatetags/__init__.py
gencal/templatetags/__init__.pyc
gencal/templatetags/gencal.py
gencal/templatetags/gencal.pyc