Metadata-Version: 1.0
Name: django-gencal
Version: 0.1
Summary: django-gencal is a resuable Django application for rendering calendars.
Home-page: http://code.justinlilly.com/django-gencal/
Author: Justin Lilly
Author-email: justin@justinlilly.com
License: UNKNOWN
Platform: UNKNOWN
Classifier: Development Status :: 3 - Alpha
Classifier: Environment :: Web Environment
Classifier: Intended Audience :: Developers
Classifier: License :: OSI Approved :: BSD License
Classifier: Operating System :: OS Independent
Classifier: Programming Language :: Python
Classifier: Framework :: Django
